lara_django/__init__.py
lara_django/urls.py
lara_django/wsgi.py
lara_django/bin/lara-django.py
lara_django/settings/__init__.py
lara_django/settings/demo.py
lara_django/settings/devel.py
lara_django/settings/settings_base.py
lara_django/static/css/app.698b5943.css
lara_django/static/css/base-stylesheet.css
lara_django/static/css/bootstrap.min.css
lara_django/static/css/chunk-vendors.45c5665a.css
lara_django/static/css/font-awesome.min.css
lara_django/static/css/responsive.css
lara_django/static/css/style.css
lara_django/static/icons/cart_icon.svg
lara_django/static/icons/container_icon.svg
lara_django/static/icons/containers_icon.svg
lara_django/static/icons/data_icon.svg
lara_django/static/icons/devices_icon.svg
lara_django/static/icons/devices_icon_.svg
lara_django/static/icons/icon_basic_shape.svg
lara_django/static/icons/labstore_icon.svg
lara_django/static/icons/people_icon.svg
lara_django/static/icons/process_icon.svg
lara_django/static/icons/projects_icon.svg
lara_django/static/icons/substances_icon.svg
lara_django/static/icons/substances_icon_.svg
lara_django/static/js/about.5e0a3e05.js
lara_django/static/js/app.0cb1c297.js
lara_django/static/js/bootstrap.min.js
lara_django/static/js/bxslider.min.js
lara_django/static/js/chunk-vendors.4d971ca8.js
lara_django/static/js/jquery.easing.1.3.min.js
lara_django/static/js/jquery.min.js
lara_django/static/js/jquery.sticky.js
lara_django/static/js/main.js
lara_django/static/js/owl.carousel.min.js
lara_django/static/js/script.slider.js
lara_django-0.2.6.data/scripts/lara-django.py
lara_django-0.2.6.dist-info/METADATA
lara_django-0.2.6.dist-info/WHEEL
lara_django-0.2.6.dist-info/top_level.txt
lara_django-0.2.6.dist-info/RECORD
