Metadata-Version: 2.1
Name: lara-django
Version: 0.2.6
Summary: LARA-django is a python django project of the Lab Automation Suite LARA - (lara.uni-greifswald.de/larasuite) 
Home-page: https://gitlab.com/LARAsuite/lara-django
Author: mark doerr
Author-email: mark.doerr@uni-greifswald.de
License: GPL
Keywords: lab automation,experiments,database,evaluation,visualisation,SiLA2,robots
Platform: UNKNOWN
Classifier: Development Status :: 3 - Alpha
Classifier: Environment :: Console
Classifier: Framework :: Django :: 3.0
Classifier: Intended Audience :: Developers
Classifier: Intended Audience :: Science/Research
Classifier: Intended Audience :: Education
Classifier: License :: OSI Approved :: GNU General Public License v3 (GPLv3)
Classifier: Operating System :: OS Independent
Classifier: Programming Language :: Python
Classifier: Programming Language :: Python :: 3.7
Classifier: Programming Language :: Python :: 3.8
Classifier: Topic :: Scientific/Engineering
Classifier: Topic :: Scientific/Engineering :: Information Analysis
Classifier: Topic :: Scientific/Engineering :: Visualization
Classifier: Topic :: Scientific/Engineering :: Bio-Informatics
Classifier: Topic :: Scientific/Engineering :: Chemistry
Requires-Dist: Django (<3.2,>=3)
Requires-Dist: django-autoadmin (<2,>=1.1)
